simple_statement/__init__.py
simple_statement/main.py
simple_statement-0.1.0.dist-info/LICENSE
simple_statement-0.1.0.dist-info/METADATA
simple_statement-0.1.0.dist-info/WHEEL
simple_statement-0.1.0.dist-info/top_level.txt
simple_statement-0.1.0.dist-info/RECORD
