Metadata-Version: 2.2
Name: simple_statement
Version: 0.1.0
Summary: A simple package that prints a custom message
Home-page: https://github.com/your_username/hello_printer
Author: ejm
Author-email: erikjmason@gmail.com
Classifier: Programming Language :: Python :: 3
Classifier: License :: OSI Approved :: MIT License
Classifier: Operating System :: OS Independent
Requires-Python: >=3.7
License-File: LICENSE
Dynamic: author
Dynamic: author-email
Dynamic: classifier
Dynamic: description
Dynamic: description-content-type
Dynamic: home-page
Dynamic: requires-python
Dynamic: summary
